nameko_neo4j/__init__.py
nameko_neo4j/graph_session.py
nameko_neo4j-0.0.1.dist-info/DESCRIPTION.rst
nameko_neo4j-0.0.1.dist-info/METADATA
nameko_neo4j-0.0.1.dist-info/RECORD
nameko_neo4j-0.0.1.dist-info/WHEEL
nameko_neo4j-0.0.1.dist-info/metadata.json
nameko_neo4j-0.0.1.dist-info/top_level.txt
nameko_neo4j-0.0.1.dist-info/zip-safe
