Metadata-Version: 2.0
Name: nameko-neo4j
Version: 0.0.1
Summary: Neo4j dependency for nameko services
Home-page: http://github.com/babylonpartners/nameko-neo4j
Author: babylon health
Author-email: ai-devops@babylonhealth.com
License: MIT License
Platform: UNKNOWN
Classifier: Programming Language :: Python
Classifier: Operating System :: MacOS :: MacOS X
Classifier: Operating System :: POSIX
Classifier: Programming Language :: Python :: 3
Classifier: Programming Language :: Python :: 3.3
Classifier: Programming Language :: Python :: 3.4
Classifier: Programming Language :: Python :: 3.5
Classifier: Programming Language :: Python :: 3.6
Classifier: Topic :: Internet
Classifier: Topic :: Software Development :: Libraries :: Python Modules
Classifier: Intended Audience :: Developers
Requires-Dist: amqp (==1.4.9)
Requires-Dist: anyjson (==0.3.3)
Requires-Dist: appdirs (==1.4.0)
Requires-Dist: astroid (==1.4.9)
Requires-Dist: coverage (==4.3.4)
Requires-Dist: enum-compat (==0.0.2)
Requires-Dist: eventlet (==0.20.1)
Requires-Dist: flake8 (==3.2.1)
Requires-Dist: greenlet (==0.4.11)
Requires-Dist: isort (==4.2.5)
Requires-Dist: kombu (==3.0.37)
Requires-Dist: lazy-object-proxy (==1.2.2)
Requires-Dist: mccabe (==0.5.3)
Requires-Dist: mock (==2.0.0)
Requires-Dist: nameko (==2.5.1)
Requires-Dist: packaging (==16.8)
Requires-Dist: path.py (==10.1)
Requires-Dist: pbr (==1.10.0)
Requires-Dist: py (==1.4.32)
Requires-Dist: py2neo (==3.1.2)
Requires-Dist: pycodestyle (==2.2.0)
Requires-Dist: pyflakes (==1.3.0)
Requires-Dist: pylint (==1.6.5)
Requires-Dist: pyparsing (==2.1.10)
Requires-Dist: pytest (==3.0.6)
Requires-Dist: PyYAML (==3.12)
Requires-Dist: requests (==2.13.0)
Requires-Dist: six (==1.10.0)
Requires-Dist: Werkzeug (==0.11.15)
Requires-Dist: wrapt (==1.10.8)
